MANIFEST.in
README.rst
setup.py
ailove_django_fias.egg-info/PKG-INFO
ailove_django_fias.egg-info/SOURCES.txt
ailove_django_fias.egg-info/dependency_links.txt
ailove_django_fias.egg-info/requires.txt
ailove_django_fias.egg-info/top_level.txt
fias/__init__.py
fias/admin.py
fias/config.py
fias/forms.py
fias/routers.py
fias/sphinxit.py
fias/urls.py
fias/version.py
fias/views.py
fias/weights.py
fias/widgets.py
fias/fields/__init__.py
fias/fields/address.py
fias/fields/uuid.py
fias/importer/__init__.py
fias/importer/archive.py
fias/importer/bulk.py
fias/importer/commands.py
fias/importer/log.py
fias/importer/table.py
fias/importer/version.py
fias/importer/loader/__init__.py
fias/importer/loader/addrobj.py
fias/importer/loader/base.py
fias/importer/loader/house.py
fias/importer/loader/houseint.py
fias/importer/loader/landmark.py
fias/importer/loader/normdoc.py
fias/importer/loader/socrbase.py
fias/locale/ru/LC_MESSAGES/django.mo
fias/management/__init__.py
fias/management/commands/__init__.py
fias/management/commands/fias.py
fias/management/commands/fias_sphinx.py
fias/management/utils/__init__.py
fias/management/utils/sphinx.py
fias/management/utils/weights.py
fias/migrations/0001_initial.py
fias/migrations/0002_auto_20150408_0853.py
fias/migrations/__init__.py
fias/models/__init__.py
fias/models/address.py
fias/models/addrobj.py
fias/models/common.py
fias/models/house.py
fias/models/landmark.py
fias/models/normdoc.py
fias/models/socrbase.py
fias/models/sphinx.py
fias/models/version.py
fias/south_migrations/0001_initial.py
fias/south_migrations/0002_add_url_fields.py
fias/south_migrations/0003_delta_xml_url_nullable.py
fias/south_migrations/0004_add_mysql_index_table.py
fias/south_migrations/0005_add_item_weight_fields.py
fias/south_migrations/0006_change_oktmo_field.py
fias/south_migrations/0007_update_db_structure.py
fias/south_migrations/__init__.py
fias/static/fias/js/fias.js
fias/static/fias/js/locale/select2_locale_ru.js
fias/static/fias/js/locale/select2_locale_uk.js
fias/templates/fias/sphinx/index.conf
fias/templates/fias/sphinx/source.conf
fias/templates/fias/sphinx/sphinx.conf
fias/templates/fias/sql/mysql/query.sql
fias/templates/fias/sql/mysql/query_post.sql
